prefect_ds/__init__.py
prefect_ds/checkpoint_handler.py
prefect_ds/flow_runner.py
prefect_ds/pandas_result_handler.py
prefect_ds/result.py
prefect_ds/task_runner.py
prefect_ds-0.1.1.dist-info/LICENSE
prefect_ds-0.1.1.dist-info/METADATA
prefect_ds-0.1.1.dist-info/WHEEL
prefect_ds-0.1.1.dist-info/top_level.txt
prefect_ds-0.1.1.dist-info/RECORD
