Metadata-Version: 2.1
Name: prefect-ds
Version: 0.1.1
Summary: Tools for making Prefect work better for typical data science workflows
Home-page: https://github.com/AndrewRook/prefect_ds
Author: Andrew Schechtman-Rook
Maintainer: Andrew Schechtman-Rook
License: Apache License 2.0
Platform: UNKNOWN
Classifier: Development Status :: 4 - Beta
Classifier: Natural Language :: English
Classifier: License :: OSI Approved :: Apache Software License
Classifier: Operating System :: OS Independent
Classifier: Programming Language :: Python :: 3 :: Only
Requires-Dist: prefect (<=0.9.2,>=0.9.0)
Requires-Dist: pandas (<=0.25.3,>=0.25.3)
Provides-Extra: dev
Requires-Dist: pytest (<=5.3.2,>=5.3.2) ; extra == 'dev'
Requires-Dist: pytest-cov (<=2.8.1,>=2.8.1) ; extra == 'dev'
